{
   "abstract" : "Module that provides shortcuts to retrieve certain information",
   "author" : [
      "Most of the code was written by Gregory Todd Williams C<<, Kjetil Kjernsmo <kjetilk@cpan.org>"
   ],
   "dynamic_config" : 0,
   "generated_by" : "ExtUtils::MakeMaker version 6.6302, CPAN::Meta::Converter version 2.120921",
   "license" : [
      "perl_5"
   ],
   "meta-spec" : {
      "url" : "http://search.cpan.org/perldoc?CPAN::Meta::Spec",
      "version" : "2"
   },
   "name" : "RDF-Helper-Properties",
   "no_index" : {
      "directory" : [
         "t",
         "inc"
      ]
   },
   "prereqs" : {
      "build" : {
         "requires" : {
            "ExtUtils::MakeMaker" : "6.59",
            "FindBin" : "0",
            "Test::More" : "0"
         }
      },
      "configure" : {
         "requires" : {
            "ExtUtils::MakeMaker" : "0"
         }
      },
      "runtime" : {
         "requires" : {
            "Any::Moose" : "0",
            "RDF::Trine" : "0.135",
            "namespace::autoclean" : "0.13",
            "perl" : "5.008"
         }
      }
   },
   "release_status" : "stable",
   "version" : "0.22"
}
